axitom/__init__.py
axitom/backprojection.py
axitom/config.py
axitom/filtering.py
axitom/phantoms.py
axitom/projection.py
axitom/utilities.py
axitom/tests/__init__.py
axitom/tests/test_axis_sym_projection.py
axitom/tests/test_map_object_to_detector_coords.py
axitom/tests/test_real_projections.py
axitom/tests/test_rotate_coordinates.py
axitom/tests/test_simulated_projections.py
axitom/tests/example_data/barrel_grad_projections_axisym.npy
axitom/tests/example_data/barrel_projections_axisym.npy
axitom/tests/example_data/proj_barrel.npy
axitom/tests/example_data/radiogram.tif
axitom/tests/example_data/radiogram.xtekct
axitom/tests/example_data/recon_by_external_software.tif
axitom/tests/example_data/settings.xtekct
axitom/tests/example_data/sim_barrel.xtekct
axitom-0.1.3.dist-info/DESCRIPTION.rst
axitom-0.1.3.dist-info/METADATA
axitom-0.1.3.dist-info/RECORD
axitom-0.1.3.dist-info/WHEEL
axitom-0.1.3.dist-info/metadata.json
axitom-0.1.3.dist-info/top_level.txt
