Metadata-Version: 2.0
Name: axitom
Version: 0.1.3
Summary: Tools for axis-symmetric cone-beam computed tomography
Home-page: https://github.com/PolymerGuy/AXITOM
Author: PolymerGuy
Author-email: sindre.n.olufsen@ntnu.no
License: UNKNOWN
Platform: UNKNOWN
Classifier: Programming Language :: Python :: 3
Classifier: License :: OSI Approved :: MIT License
Classifier: Operating System :: OS Independent
Requires-Dist: imageio
Requires-Dist: matplotlib
Requires-Dist: natsort
Requires-Dist: nose
Requires-Dist: numpy
Requires-Dist: scikit-image
Requires-Dist: scipy
